LICENSE
MANIFEST.in
README.md
requirements.txt
setup.cfg
setup.py
versioneer.py
intake_streamz/__init__.py
intake_streamz/_version.py
intake_streamz/source.py
intake_streamz.egg-info/PKG-INFO
intake_streamz.egg-info/SOURCES.txt
intake_streamz.egg-info/dependency_links.txt
intake_streamz.egg-info/entry_points.txt
intake_streamz.egg-info/not-zip-safe
intake_streamz.egg-info/requires.txt
intake_streamz.egg-info/top_level.txt