Metadata-Version: 1.2
Name: intake-streamz
Version: 0.0.1
Summary: streamz plugin for Intake
Home-page: https://github.com/intake/intake-streamz
Maintainer: Martin Durant
Maintainer-email: mdurant@anaconda.com
License: BSD
Platform: UNKNOWN
